biocontext/__init__.py
biocontext/client.py
biocontext/server.py
biocontext/registry/__init__.py
biocontext/registry/client.py
biocontext/registry/schema.py
biocontext/utils/__init__.py
biocontext/utils/string.py
biocontext-0.1.3.dist-info/METADATA
biocontext-0.1.3.dist-info/WHEEL
biocontext-0.1.3.dist-info/licenses/LICENSE
biocontext-0.1.3.dist-info/RECORD
