Metadata-Version: 2.4
Name: biocontext
Version: 0.1.3
Summary: Python package to integrate BioContext with the BioCypher ecosystem.
Project-URL: Homepage, https://biocypher.github.io/biocontext/
Project-URL: Repository, https://github.com/biocypher/biocontext
Project-URL: Documentation, https://biocypher.github.io/biocontext/
Author-email: Sebastian Lobentanzer <sebastian.lobentanzer@gmail.com>
License-File: LICENSE
Keywords: python
Classifier: Intended Audience :: Developers
Classifier: Programming Language :: Python
Classifier: Programming Language :: Python :: 3
Classifier: Programming Language :: Python :: 3.11
Classifier: Programming Language :: Python :: 3.12
Classifier: Programming Language :: Python :: 3.13
Classifier: Topic :: Software Development :: Libraries :: Python Modules
Requires-Python: <4.0,>=3.11
Requires-Dist: fastmcp>=2.4.0
Requires-Dist: httpx>=0.28.1
Requires-Dist: pydantic>=2.11.4
Requires-Dist: pyyaml>=6.0.2
